simwrapper/MiniFileServer.py
simwrapper/__init__.py
simwrapper/cli.py
simwrapper/sites.py
simwrapper/static/404.html
simwrapper/static/404.html.bak
simwrapper/static/README.md
simwrapper/static/icon-atlas.png
simwrapper/static/index.html
simwrapper/static/tu-logo-circle.jpg
simwrapper/static/tu-logo-circle.png
simwrapper/static/tu-logo.png
simwrapper/static/vta-logo.png
simwrapper/static/assets/AggregateDatasetStreamer.worker-e7e3995e.js
simwrapper/static/assets/AggregateDatasetStreamer.worker-e7e3995e.js.map
simwrapper/static/assets/AggregateOd-12159462.css
simwrapper/static/assets/AggregateOd-89d1b1fd.js
simwrapper/static/assets/AggregateOd-89d1b1fd.js.map
simwrapper/static/assets/CalculationTable-569a9b13.css
simwrapper/static/assets/CalculationTable-6d5fac92.js
simwrapper/static/assets/CalculationTable-6d5fac92.js.map
simwrapper/static/assets/CarrierViewer-291f4bd9.css
simwrapper/static/assets/CarrierViewer-b4fd7190.js
simwrapper/static/assets/CarrierViewer-b4fd7190.js.map
simwrapper/static/assets/CollapsiblePanel-ab362bfb.js
simwrapper/static/assets/CollapsiblePanel-ab362bfb.js.map
simwrapper/static/assets/CollapsiblePanel-be786996.css
simwrapper/static/assets/ColorsAndWidths-450f80df.js
simwrapper/static/assets/ColorsAndWidths-450f80df.js.map
simwrapper/static/assets/Coords-23d23a7c.js
simwrapper/static/assets/Coords-23d23a7c.js.map
simwrapper/static/assets/CsvGzipParser.worker-10b16701.js
simwrapper/static/assets/CsvGzipParser.worker-10b16701.js.map
simwrapper/static/assets/DashBoard-36d4d4f5.css
simwrapper/static/assets/DashBoard-474d8af5.js
simwrapper/static/assets/DashBoard-474d8af5.js.map
simwrapper/static/assets/DashboardDataManager-13d94a64.js
simwrapper/static/assets/DashboardDataManager-13d94a64.js.map
simwrapper/static/assets/DataFetcher.worker-3f9d49f7.js
simwrapper/static/assets/DataFetcher.worker-3f9d49f7.js.map
simwrapper/static/assets/DrawingTool-bd1d0a33.js
simwrapper/static/assets/DrawingTool-bd1d0a33.js.map
beam_viewer-1.10.0.dist-info/LICENSE.txt
beam_viewer-1.10.0.dist-info/METADATA
beam_viewer-1.10.0.dist-info/WHEEL
beam_viewer-1.10.0.dist-info/entry_points.txt
beam_viewer-1.10.0.dist-info/top_level.txt
beam_viewer-1.10.0.dist-info/RECORD
