Metadata-Version: 2.1
Name: beam-viewer
Version: 1.10.0
Summary: Python support library for SimWrapper BEAM data visualization tool
Home-page: https://github.com/simwrapper/beam-python-tools
Author: Billy Charlton
Author-email: billy@okbecause.com
License: GPLv3
Classifier: License :: OSI Approved :: GNU General Public License (GPL)
Classifier: Programming Language :: Python :: 3
License-File: LICENSE.txt
Requires-Dist: Click
